MANIFEST.in
README.rst
setup.py
django_loginza.egg-info/PKG-INFO
django_loginza.egg-info/SOURCES.txt
django_loginza.egg-info/dependency_links.txt
django_loginza.egg-info/not-zip-safe
django_loginza.egg-info/requires.txt
django_loginza.egg-info/top_level.txt
loginza/__init__.py
loginza/admin.py
loginza/authentication.py
loginza/decorators.py
loginza/models.py
loginza/signals.py
loginza/tests.py
loginza/urls.py
loginza/views.py
loginza/conf/__init__.py
loginza/conf/settings.py
loginza/locale/ru/LC_MESSAGES/django.mo
loginza/locale/ru/LC_MESSAGES/django.po
loginza/templatetags/__init__.py
loginza/templatetags/loginza_widget.py