Metadata-Version: 1.1
Name: django-loginza
Version: 0.3.7
Summary: Django application for Loginza service
Home-page: https://github.com/vgarvardt/django-loginza
Author: Vladimir Garvardt
Author-email: vgarvardt@gmail.com
License: UNKNOWN
Platform: UNKNOWN
Classifier: Development Status :: 5 - Production/Stable
Classifier: Environment :: Web Environment
Classifier: Intended Audience :: Developers
Classifier: License :: OSI Approved :: BSD License
Classifier: Operating System :: OS Independent
Classifier: Programming Language :: Python
Classifier: Framework :: Django
